MANIFEST.in
README.rst
UNLICENSE.txt
requirements.txt
setup.cfg
setup.py
test-requirements.txt
django_generic_counter/__init__.py
django_generic_counter/admin.py
django_generic_counter/models.py
django_generic_counter.egg-info/PKG-INFO
django_generic_counter.egg-info/SOURCES.txt
django_generic_counter.egg-info/dependency_links.txt
django_generic_counter.egg-info/namespace_packages.txt
django_generic_counter.egg-info/not-zip-safe
django_generic_counter.egg-info/requires.txt
django_generic_counter.egg-info/top_level.txt
django_generic_counter/migrations/0001_initial.py
django_generic_counter/migrations/0002_auto_20150911_0900.py
django_generic_counter/migrations/0003_alter_count_to_bigint.py
django_generic_counter/migrations/__init__.py
django_generic_counter/south_migrations/0001_initial.py
django_generic_counter/south_migrations/0002_auto__add_unique_counter_name.py
django_generic_counter/south_migrations/0003_auto__chg_field_counter_count.py
django_generic_counter/south_migrations/__init__.py