Metadata-Version: 1.1
Name: django-generic-counter
Version: 0.0.9
Summary: |Build Status| |Coverage Status|
